mux2to1p.v
module mux2to1p (input sel, input x , input y, output z);
  // 2 to 1 mux at structural level logic
  
  wire selnot, xnandsel, ynandsel, xynand;
 
  // NOT gate inverts select line input
  not selnot (selnot, sel);
    // NAND gates for selection 
  nand x_nandsel (xnandsel, x, selnot);
    //NAND between input x and inverted select line
  nand y_nandsel (ynandsel, y, sel);
    
  nand xy_nand (xynand, xnandsel, ynandsel);
    // Assigning the output of the NOR gate to the output port
  assign z = xynand;
endmodule
// test  file is mux2to1ptest.v

mux2to1ptestb.v
`timescale 1ns / 1ns
`include "mux2to1p.v"
module mux2to1str_tb;
  reg sel;
  reg x;
  reg y;
  wire z;
  //Inputs & Outputs
    mux2to1p uut (.sel(sel), .x(x), .y(y), .z(z));
  
  initial begin
    $dumpfile("mux2to1p.vcd");
    $dumpvars(0, mux2to1str_tb);
        // Test case - sel=0, x=0, y=0
    sel = 0;
    x = 0;
    y = 0;
    #5;
    $display("Test case - sel=0, x=0, y=0: z=%y", z);
    
    // Test case - sel=0, x=0, y=1
    sel = 0;
    x = 0;
    y = 1;
    #5;
    $display("Test case - sel=0, x=0, y=1: z=%y", z);
    
    // Test case - sel=0, x=1, y=0
    sel = 0;
    x = 1;
    y = 0;
    #5;
    $display("Test case - sel=0, x=1, y=0: z=%b", z);
    

    sel = 0;
    x = 1;
    y = 1;
    #5;
    $display("Test case - sel=0, x=1, y=1: z=%y", z);
    
   
    sel = 1;
    x = 0;
    y = 0;
    #5;
    $display("Test case - sel=1, x=0, y=0: z=%y", z);
    
    
    sel = 1;
    x = 0;
    y = 1;
    #5;
    $display("Test case - sel=1, x=0, y=1: z=%b", z);
    
    
    sel = 1;
    x = 1;
    y= 0;
    #5;
    $display("Test case - sel=1, a=x, y=0: z=%y", z);
    
   
    sel = 1;
    x = 1;
    y = 1;
    #5;
    $display("Test case - sel=1, x=1, y=1: z=%y", z);
    
    $finish;
  end
endmodule

mux2to1p.vcd
$date
	Thu May 04 15:12:34 2023
$end
$version
	Icarus Verilog
$end
$timescale
	1ns
$end
$scope module mux2to1str_tb $end
$var wire 1 ! z $end
$var reg 1 " sel $end
$var reg 1 # x $end
$var reg 1 $ y $end
$scope module uut $end
$var wire 1 % sel $end
$var wire 1 & selnot $end
$var wire 1 ' x $end
$var wire 1 ( xnandsel $end
$var wire 1 ) xynand $end
$var wire 1 * y $end
$var wire 1 + ynandsel $end
$var wire 1 ! z $end
$upscope $end
$upscope $end
$enddefinitions $end
#0
$dumpvars
1+
0*
0)
1(
0'
1&
0%
0$
0#
0"
0!
$end
#5
1$
1*
#10
1!
1)
0(
0$
0*
1#
1'
#15
1$
1*
#20
0!
0)
1(
0&
0$
0*
0#
0'
1"
1%
#25
1!
1)
0+
1$
1*
#30
0!
0)
1+
0$
0*
1#
1'
#35
1!
1)
0+
1$
1*
